Metadata-Version: 2.1
Name: stusystem
Version: 0.0.5
Summary:  private utils.
Home-page: https://github.com/BaobaoAndDabao/stusystem.git
Author: Vinceeeeee9
Author-email: wenzhihaosuot@163.com
License: MIT Licence
Keywords: pip,stusystem
Platform: any
